Metadata-Version: 1.0
Name: catstest
Version: 0.1
Summary: Python Package Test
Home-page: UNKNOWN
Author: Amos Voron
Author-email: UNKNOWN
License: UNKNOWN
Platform: UNKNOWN
